clscidapi/__init__.py
clscidapi/__main__.py
clscidapi/api.py
clscidapi/config.py
clscidapi/models.py
clscidapi-0.1.0.dist-info/LICENSE
clscidapi-0.1.0.dist-info/METADATA
clscidapi-0.1.0.dist-info/WHEEL
clscidapi-0.1.0.dist-info/top_level.txt
clscidapi-0.1.0.dist-info/RECORD
