Metadata-Version: 2.1
Name: clscidapi
Version: 0.1.0
Summary: A simple HTTP API that supports lookups of CAIC classic Field Report IDs.
Author: John Gorman
License: MIT License
Project-URL: Homepage, https://github.com/gormaniac/clscidapi
Requires-Python: >=3.11
License-File: LICENSE
Requires-Dist: fastapi (==0.96.*)
Requires-Dist: pydantic (==1.10.*)
Requires-Dist: uvicorn (==0.22.*)
